pyfolk/__init__.py
pyfolk/userapi.py
pyfolk/pypack/ai/gesturedetect.cp37-win_amd64.pyd
pyfolk/pypack/ai/qrcodedetect.cp37-win_amd64.pyd
pyfolk/pypack/ai/targetdetect.cp37-win_amd64.pyd
pyfolk/pypack/ai/tracker.cp37-win_amd64.pyd
pyfolk/pypack/folk/commandprocessor.cp37-win_amd64.pyd
pyfolk/pypack/folk/controlserver.cp37-win_amd64.pyd
pyfolk/pypack/folk/extendprotocol.cp37-win_amd64.pyd
pyfolk/pypack/folk/mavlink.cp37-win_amd64.pyd
pyfolk/pypack/folk/msganalyzer.cp37-win_amd64.pyd
pyfolk/pypack/folk/msganalyzerjson.cp37-win_amd64.pyd
pyfolk/pypack/folk/partandequipment.cp37-win_amd64.pyd
pyfolk/pypack/folk/stateprocessor.cp37-win_amd64.pyd
pyfolk/pypack/folk/taskprocessor.cp37-win_amd64.pyd
pyfolk/pypack/folk/uwb.cp37-win_amd64.pyd
pyfolk/pypack/system/buffer.cp37-win_amd64.pyd
pyfolk/pypack/system/command.cp37-win_amd64.pyd
pyfolk/pypack/system/communicationcontroller.cp37-win_amd64.pyd
pyfolk/pypack/system/communicationcontrollerfactory.cp37-win_amd64.pyd
pyfolk/pypack/system/datacenter.cp37-win_amd64.pyd
pyfolk/pypack/system/dispatcher.cp37-win_amd64.pyd
pyfolk/pypack/system/firmwareanalyzer.cp37-win_amd64.pyd
pyfolk/pypack/system/logcontroller.cp37-win_amd64.pyd
pyfolk/pypack/system/mavcrc.cp37-win_amd64.pyd
pyfolk/pypack/system/network.cp37-win_amd64.pyd
pyfolk/pypack/system/networkcontroller.cp37-win_amd64.pyd
pyfolk/pypack/system/part2equipment.cp37-win_amd64.pyd
pyfolk/pypack/system/rvscontroller.cp37-win_amd64.pyd
pyfolk/pypack/system/serialcontroller.cp37-win_amd64.pyd
pyfolk/pypack/system/state.cp37-win_amd64.pyd
pyfolk/pypack/system/task.cp37-win_amd64.pyd
pyfolk/pypack/system/taskcontroller.cp37-win_amd64.pyd
pyfolk/pypack/system/videocontroller.cp37-win_amd64.pyd
pyfolk/pypack/system/videocontrollerprocess.cp37-win_amd64.pyd
pyfolk-1.0.0.data/data/Lib/site-packages/pyfolk/FolkPlayer/FolkPlayer.exe
pyfolk-1.0.0.data/data/Lib/site-packages/pyfolk/FolkPlayer/UnityCrashHandler64.exe
pyfolk-1.0.0.data/data/Lib/site-packages/pyfolk/FolkPlayer/UnityPlayer.dll
pyfolk-1.0.0.dist-info/METADATA
pyfolk-1.0.0.dist-info/WHEEL
pyfolk-1.0.0.dist-info/top_level.txt
pyfolk-1.0.0.dist-info/RECORD
