Metadata-Version: 2.1
Name: pyfolk
Version: 1.0.0
Summary: Folk Edu package
Home-page: UNKNOWN
Author: HighGreat
Author-email: highgreat@hg-fly.com
License: UNKNOWN
Platform: UNKNOWN
Classifier: Intended Audience :: Education
Classifier: Programming Language :: Python
Classifier: Programming Language :: Python :: 3
Classifier: Programming Language :: Python :: 3.5
Classifier: Programming Language :: Python :: 3.6
Classifier: Programming Language :: Python :: 3.7
Classifier: Programming Language :: Python :: 3.8
Classifier: Programming Language :: Python :: 3 :: Only
Classifier: Operating System :: Microsoft :: Windows
Requires-Python: >=3.5
Requires-Dist: numpy (==1.18.2)
Requires-Dist: opencv-contrib-python (==3.4.8.29)
Requires-Dist: gevent (==20.6.1)
